markdown_grapher.py
markdown_grapher-0.0.2.dist-info/LICENSE
markdown_grapher-0.0.2.dist-info/METADATA
markdown_grapher-0.0.2.dist-info/WHEEL
markdown_grapher-0.0.2.dist-info/entry_points.txt
markdown_grapher-0.0.2.dist-info/top_level.txt
markdown_grapher-0.0.2.dist-info/RECORD
